eagleeyeair/__init__.py
eagleeyeair/__main__.py
eagleeyeair/eagle_eye_api.py
eagleeyeair/pos.py
eagleeyeair/resources.py
eagleeyeair/wallet.py
eagleeyeair-0.1.7.dist-info/LICENSE.txt
eagleeyeair-0.1.7.dist-info/METADATA
eagleeyeair-0.1.7.dist-info/WHEEL
eagleeyeair-0.1.7.dist-info/entry_points.txt
eagleeyeair-0.1.7.dist-info/top_level.txt
eagleeyeair-0.1.7.dist-info/RECORD
