Metadata-Version: 2.1
Name: eagleeyeair
Version: 0.1.7
Summary: Python API client library for eagleeye
Home-page: https://github.com/eagleeyeair/eagleeyeair
Author: Cheng, Gang
Author-email: cg1101@gmail.com
License: MIT
Platform: UNKNOWN
Classifier: License :: OSI Approved :: MIT License
Classifier: Programming Language :: Python :: 3
